{
  "resort": "lakelouise",
  "resortName": "Lake Louise",
  "date": "2026-02-01",
  "timestamp": "2026-02-01T09:39:20.065Z",
  "lastUpdated": "2026-02-01T09:39:20.065Z",
  "provider": "canadian-big3",
  "apiProvider": "ski-louise-xml",
  "conditions": "Overcast",
  "operatingStatus": "Open",
  "snowfall": {
    "overnight_inches": 2.4,
    "overnight_cm": 6,
    "24hour_inches": 2.8,
    "24hour_cm": 7,
    "48hour_inches": 3.9,
    "48hour_cm": 10,
    "7day_inches": 5.5,
    "7day_cm": 14,
    "season_total_inches": 237.8,
    "season_total_cm": 604
  },
  "baseDepth": {
    "inches": 65,
    "cm": 165,
    "lower_inches": 49.2,
    "lower_cm": 125,
    "upper_inches": 65,
    "upper_cm": 165
  },
  "terrain": {
    "totalTrails": 170,
    "openTrails": 170,
    "groomedTrails": 39,
    "totalLifts": 13,
    "openLifts": 13
  },
  "currentConditions": {
    "temperature_c": -1,
    "temperature_f": 30.2
  },
  "forecast": {
    "locations": [
      {
        "name": "Base",
        "elevation": null,
        "today": {
          "high_f": 32,
          "high_c": 0,
          "low_f": 32,
          "low_c": 0,
          "description": "Cloud/Sun/Mixed",
          "snowfall_day_inches": 0,
          "snowfall_night_inches": 0
        },
        "forecast_days": [
          {
            "date": "2026-02-01T09:39:20.068Z",
            "high_f": 32,
            "high_c": 0,
            "low_f": 32,
            "low_c": 0,
            "description": "Cloud/Sun/Mixed",
            "snowfall_day_inches": 0,
            "snowfall_night_inches": 0
          },
          {
            "date": "2026-02-02T09:39:20.068Z",
            "high_f": 32,
            "high_c": 0,
            "low_f": 32,
            "low_c": 0,
            "description": "Snow",
            "snowfall_day_inches": 0,
            "snowfall_night_inches": 0
          },
          {
            "date": "2026-02-03T09:39:20.068Z",
            "high_f": 32,
            "high_c": 0,
            "low_f": 32,
            "low_c": 0,
            "description": "Snow",
            "snowfall_day_inches": 0,
            "snowfall_night_inches": 0
          },
          {
            "date": "2026-02-04T09:39:20.068Z",
            "high_f": 32,
            "high_c": 0,
            "low_f": 32,
            "low_c": 0,
            "description": "Sunny",
            "snowfall_day_inches": 0,
            "snowfall_night_inches": 0
          },
          {
            "date": "2026-02-05T09:39:20.068Z",
            "high_f": 32,
            "high_c": 0,
            "low_f": 32,
            "low_c": 0,
            "description": "Snow",
            "snowfall_day_inches": 0,
            "snowfall_night_inches": 0
          },
          {
            "date": "2026-02-06T09:39:20.068Z",
            "high_f": 32,
            "high_c": 0,
            "low_f": 32,
            "low_c": 0,
            "description": "Sunny",
            "snowfall_day_inches": 0,
            "snowfall_night_inches": 0
          }
        ]
      }
    ]
  }
}