{
  "resort": "buttermilk",
  "resortName": "Buttermilk",
  "date": "2026-02-22",
  "generated": "2026-02-22T16:47:56.702Z",
  "rawData": {
    "terrain": {
      "stats": {
        "openTrails": {
          "today": 49,
          "yesterday": 49,
          "delta": 0
        },
        "groomedTrails": {
          "today": 27,
          "yesterday": 0,
          "delta": 27
        },
        "totalTrails": 52
      },
      "newlyOpened": [],
      "newlyClosed": [],
      "newlyGroomed": [
        {
          "name": "Baby Doe",
          "difficulty": "Blue",
          "area": "Main"
        },
        {
          "name": "Bear",
          "difficulty": "Blue",
          "area": "Main"
        },
        {
          "name": "Columbine",
          "difficulty": "Blue",
          "area": "Main"
        },
        {
          "name": "Homestead Road",
          "difficulty": "Green",
          "area": "Main"
        },
        {
          "name": "Lover's Lane",
          "difficulty": "Blue",
          "area": "Main"
        },
        {
          "name": "Midway Avenue",
          "difficulty": "Blue",
          "area": "Main"
        },
        {
          "name": "No Problem",
          "difficulty": "Blue",
          "area": "Main"
        },
        {
          "name": "Panda Hill",
          "difficulty": "Green",
          "area": "Main"
        },
        {
          "name": "Ridge Trail",
          "difficulty": "Blue",
          "area": "Main"
        },
        {
          "name": "Savio (Upper)",
          "difficulty": "Blue",
          "area": "Main"
        },
        {
          "name": "Family Cross",
          "difficulty": "TerrainPark",
          "area": "Pipes/Parks"
        },
        {
          "name": "Jacob's Ladder",
          "difficulty": "TerrainPark",
          "area": "Pipes/Parks"
        },
        {
          "name": "Mini Pipe",
          "difficulty": "TerrainPark",
          "area": "Pipes/Parks"
        },
        {
          "name": "Red's Rover",
          "difficulty": "TerrainPark",
          "area": "Pipes/Parks"
        },
        {
          "name": "Teaser Park",
          "difficulty": "TerrainPark",
          "area": "Pipes/Parks"
        },
        {
          "name": "Uncle Chucks Glades",
          "difficulty": "TerrainPark",
          "area": "Pipes/Parks"
        },
        {
          "name": "Buckskin",
          "difficulty": "Blue",
          "area": "Tiehack"
        },
        {
          "name": "Eagle Hill",
          "difficulty": "Blue",
          "area": "Tiehack"
        },
        {
          "name": "Klaus' Way",
          "difficulty": "Black",
          "area": "Tiehack"
        },
        {
          "name": "Magic Carpet",
          "difficulty": "Blue",
          "area": "Tiehack"
        },
        {
          "name": "Rabbit Run",
          "difficulty": "Blue",
          "area": "Tiehack"
        },
        {
          "name": "Racer's Edge",
          "difficulty": "Black",
          "area": "Tiehack"
        },
        {
          "name": "Sterner Gulch",
          "difficulty": "Blue",
          "area": "Tiehack"
        },
        {
          "name": "Big Face Hollow",
          "difficulty": "Blue",
          "area": "West Buttermilk"
        },
        {
          "name": "Larkspur",
          "difficulty": "Green",
          "area": "West Buttermilk"
        },
        {
          "name": "Tom's Thumb",
          "difficulty": "Green",
          "area": "West Buttermilk"
        },
        {
          "name": "Westward Ho",
          "difficulty": "Green",
          "area": "West Buttermilk"
        }
      ],
      "ungroomed": []
    },
    "lifts": {
      "available": true,
      "yesterday": {
        "date": "2026-02-21",
        "avgWaitTime": 0,
        "maxWaitTime": 0,
        "totalLiftsTracked": 5,
        "busiest": []
      }
    }
  },
  "computedInsights": {
    "flags": {
      "hasNewTrails": false,
      "significantGroomingIncrease": false,
      "highLiftDemand": false
    },
    "alerts": [
      "27 trails freshly groomed"
    ],
    "trends": [],
    "recommendations": [
      "Fresh corduroy on Baby Doe - perfect for intermediate skiers",
      "Fresh corduroy on Bear - perfect for intermediate skiers",
      "Fresh corduroy on Columbine - perfect for intermediate skiers"
    ]
  },
  "morningBrief": null,
  "errors": []
}