{
  "Date": "2026-02-15T05:33:33-0500",
  "GroomingAreas": [
    {
      "Name": "Glades",
      "Trails": [
        {
          "Name": "Buck Shot",
          "Status": "Closed",
          "IsOpen": false,
          "Difficulty": "Intermediate",
          "IsGroomed": false,
          "GroomingStatus": null,
          "TrailType": "Skiing",
          "Moguls": "No",
          "Glades": "Yes",
          "Touring": "No",
          "RunOfTheDay": "No",
          "SnowMaking": "No",
          "NightSkiing": "No",
          "Nordic": "No",
          "_inspectorGrooming": "No"
        },
        {
          "Name": "Cabin Fever",
          "Status": "Open",
          "IsOpen": true,
          "Difficulty": "Expert",
          "IsGroomed": false,
          "GroomingStatus": null,
          "TrailType": "Skiing",
          "Moguls": "No",
          "Glades": "Yes",
          "Touring": "No",
          "RunOfTheDay": "No",
          "SnowMaking": "No",
          "NightSkiing": "No",
          "Nordic": "No",
          "_inspectorGrooming": "No"
        },
        {
          "Name": "Dancing Bear",
          "Status": "Open",
          "IsOpen": true,
          "Difficulty": "Expert",
          "IsGroomed": false,
          "GroomingStatus": null,
          "TrailType": "Skiing",
          "Moguls": "No",
          "Glades": "Yes",
          "Touring": "No",
          "RunOfTheDay": "No",
          "SnowMaking": "No",
          "NightSkiing": "No",
          "Nordic": "No",
          "_inspectorGrooming": "No"
        },
        {
          "Name": "Daniel's Web",
          "Status": "Open",
          "IsOpen": true,
          "Difficulty": "Easy",
          "IsGroomed": false,
          "GroomingStatus": null,
          "TrailType": "Skiing",
          "Moguls": "No",
          "Glades": "Yes",
          "Touring": "No",
          "RunOfTheDay": "No",
          "SnowMaking": "No",
          "NightSkiing": "No",
          "Nordic": "No",
          "_inspectorGrooming": "No"
        },
        {
          "Name": "Diamond in the Rough",
          "Status": "Open",
          "IsOpen": true,
          "Difficulty": "Expert",
          "IsGroomed": false,
          "GroomingStatus": null,
          "TrailType": "Skiing",
          "Moguls": "No",
          "Glades": "Yes",
          "Touring": "No",
          "RunOfTheDay": "No",
          "SnowMaking": "No",
          "NightSkiing": "No",
          "Nordic": "No",
          "_inspectorGrooming": "No"
        },
        {
          "Name": "Eclipse",
          "Status": "Open",
          "IsOpen": true,
          "Difficulty": "Intermediate",
          "IsGroomed": false,
          "GroomingStatus": null,
          "TrailType": "Skiing",
          "Moguls": "No",
          "Glades": "Yes",
          "Touring": "No",
          "RunOfTheDay": "No",
          "SnowMaking": "No",
          "NightSkiing": "No",
          "Nordic": "No",
          "_inspectorGrooming": "No"
        },
        {
          "Name": "Emerald Forest",
          "Status": "Open",
          "IsOpen": true,
          "Difficulty": "Intermediate",
          "IsGroomed": false,
          "GroomingStatus": null,
          "TrailType": "Skiing",
          "Moguls": "No",
          "Glades": "Yes",
          "Touring": "No",
          "RunOfTheDay": "No",
          "SnowMaking": "No",
          "NightSkiing": "No",
          "Nordic": "No",
          "_inspectorGrooming": "No"
        },
        {
          "Name": "Free Fall Gully",
          "Status": "Open",
          "IsOpen": true,
          "Difficulty": "Extreme Terrain",
          "IsGroomed": false,
          "GroomingStatus": null,
          "TrailType": "Skiing",
          "Moguls": "No",
          "Glades": "Yes",
          "Touring": "No",
          "RunOfTheDay": "No",
          "SnowMaking": "No",
          "NightSkiing": "No",
          "Nordic": "No",
          "_inspectorGrooming": "No"
        },
        {
          "Name": "Kidderbrook Ravine",
          "Status": "Open",
          "IsOpen": true,
          "Difficulty": "Extreme Terrain",
          "IsGroomed": false,
          "GroomingStatus": null,
          "TrailType": "Skiing",
          "Moguls": "No",
          "Glades": "Yes",
          "Touring": "No",
          "RunOfTheDay": "No",
          "SnowMaking": "No",
          "NightSkiing": "No",
          "Nordic": "No",
          "_inspectorGrooming": "No"
        },
        {
          "Name": "Moonbeam",
          "Status": "Open",
          "IsOpen": true,
          "Difficulty": "Intermediate",
          "IsGroomed": false,
          "GroomingStatus": null,
          "TrailType": "Skiing",
          "Moguls": "No",
          "Glades": "Yes",
          "Touring": "No",
          "RunOfTheDay": "No",
          "SnowMaking": "No",
          "NightSkiing": "No",
          "Nordic": "No",
          "_inspectorGrooming": "No"
        },
        {
          "Name": "Moondance",
          "Status": "Open",
          "IsOpen": true,
          "Difficulty": "Extreme Terrain",
          "IsGroomed": false,
          "GroomingStatus": null,
          "TrailType": "Skiing",
          "Moguls": "No",
          "Glades": "Yes",
          "Touring": "No",
          "RunOfTheDay": "No",
          "SnowMaking": "No",
          "NightSkiing": "No",
          "Nordic": "No",
          "_inspectorGrooming": "No"
        },
        {
          "Name": "Shred Wood Forest",
          "Status": "Open",
          "IsOpen": true,
          "Difficulty": "Extreme Terrain",
          "IsGroomed": false,
          "GroomingStatus": null,
          "TrailType": "Skiing",
          "Moguls": "No",
          "Glades": "Yes",
          "Touring": "No",
          "RunOfTheDay": "No",
          "SnowMaking": "No",
          "NightSkiing": "No",
          "Nordic": "No",
          "_inspectorGrooming": "No"
        },
        {
          "Name": "Squirrel's Nest",
          "Status": "Open",
          "IsOpen": true,
          "Difficulty": "Extreme Terrain",
          "IsGroomed": false,
          "GroomingStatus": null,
          "TrailType": "Skiing",
          "Moguls": "No",
          "Glades": "Yes",
          "Touring": "No",
          "RunOfTheDay": "No",
          "SnowMaking": "No",
          "NightSkiing": "No",
          "Nordic": "No",
          "_inspectorGrooming": "No"
        },
        {
          "Name": "Test Pilot",
          "Status": "Open",
          "IsOpen": true,
          "Difficulty": "Extreme Terrain",
          "IsGroomed": false,
          "GroomingStatus": null,
          "TrailType": "Skiing",
          "Moguls": "No",
          "Glades": "Yes",
          "Touring": "No",
          "RunOfTheDay": "No",
          "SnowMaking": "No",
          "NightSkiing": "No",
          "Nordic": "No",
          "_inspectorGrooming": "No"
        },
        {
          "Name": "Vertigo",
          "Status": "Open",
          "IsOpen": true,
          "Difficulty": "Extreme Terrain",
          "IsGroomed": false,
          "GroomingStatus": null,
          "TrailType": "Skiing",
          "Moguls": "No",
          "Glades": "Yes",
          "Touring": "No",
          "RunOfTheDay": "No",
          "SnowMaking": "No",
          "NightSkiing": "No",
          "Nordic": "No",
          "_inspectorGrooming": "No"
        },
        {
          "Name": "West Pilot",
          "Status": "Open",
          "IsOpen": true,
          "Difficulty": "Intermediate",
          "IsGroomed": false,
          "GroomingStatus": null,
          "TrailType": "Skiing",
          "Moguls": "No",
          "Glades": "Yes",
          "Touring": "No",
          "RunOfTheDay": "No",
          "SnowMaking": "No",
          "NightSkiing": "No",
          "Nordic": "No",
          "_inspectorGrooming": "No"
        },
        {
          "Name": "Why Not",
          "Status": "Open",
          "IsOpen": true,
          "Difficulty": "Extreme Terrain",
          "IsGroomed": false,
          "GroomingStatus": null,
          "TrailType": "Skiing",
          "Moguls": "No",
          "Glades": "Yes",
          "Touring": "No",
          "RunOfTheDay": "No",
          "SnowMaking": "No",
          "NightSkiing": "No",
          "Nordic": "No",
          "_inspectorGrooming": "No"
        }
      ],
      "Lifts": []
    },
    {
      "Name": "Learning Areas",
      "Trails": [
        {
          "Name": "Downtowner",
          "Status": "Open",
          "IsOpen": true,
          "Difficulty": "Easy",
          "IsGroomed": false,
          "GroomingStatus": null,
          "TrailType": "Skiing",
          "Moguls": "No",
          "Glades": "No",
          "Touring": "No",
          "RunOfTheDay": "No",
          "SnowMaking": "No",
          "NightSkiing": "No",
          "Nordic": "No",
          "_inspectorGrooming": "No"
        },
        {
          "Name": "Stage 1",
          "Status": "Open",
          "IsOpen": true,
          "Difficulty": "Easy",
          "IsGroomed": true,
          "GroomingStatus": "Yes",
          "TrailType": "Skiing",
          "Moguls": "No",
          "Glades": "No",
          "Touring": "No",
          "RunOfTheDay": "No",
          "SnowMaking": "No",
          "NightSkiing": "No",
          "Nordic": "No",
          "_inspectorGrooming": "Yes"
        },
        {
          "Name": "Tyrolienne",
          "Status": "Open",
          "IsOpen": true,
          "Difficulty": "Easy",
          "IsGroomed": true,
          "GroomingStatus": "Yes",
          "TrailType": "Skiing",
          "Moguls": "No",
          "Glades": "No",
          "Touring": "No",
          "RunOfTheDay": "No",
          "SnowMaking": "No",
          "NightSkiing": "No",
          "Nordic": "No",
          "_inspectorGrooming": "Yes"
        },
        {
          "Name": "Village Walk",
          "Status": "Open",
          "IsOpen": true,
          "Difficulty": "Easy",
          "IsGroomed": true,
          "GroomingStatus": "Yes",
          "TrailType": "Skiing",
          "Moguls": "No",
          "Glades": "No",
          "Touring": "No",
          "RunOfTheDay": "No",
          "SnowMaking": "No",
          "NightSkiing": "No",
          "Nordic": "No",
          "_inspectorGrooming": "Yes"
        }
      ],
      "Lifts": [
        {
          "Name": "Cub Carpet",
          "Status": "Closed",
          "IsOpen": false,
          "LiftType": "Magic Carpet",
          "WaitTime": "--",
          "WaitTimeString": "-- min",
          "FirstTracks": "No",
          "Hours": {
            "Sunday": {
              "Open": "8:30 AM",
              "Close": "4:00 PM"
            },
            "Monday": {
              "Open": "9:00 AM",
              "Close": "4:00 PM"
            },
            "Tuesday": {
              "Open": "9:00 AM",
              "Close": "4:00 PM"
            },
            "Wednesday": {
              "Open": "9:00 AM",
              "Close": "4:00 PM"
            },
            "Thursday": {
              "Open": "9:00 AM",
              "Close": "4:00 PM"
            },
            "Friday": {
              "Open": "9:00 AM",
              "Close": "4:00 PM"
            },
            "Saturday": {
              "Open": "8:30 AM",
              "Close": "4:00 PM"
            }
          }
        },
        {
          "Name": "Villager",
          "Status": "Closed",
          "IsOpen": false,
          "LiftType": "Double",
          "WaitTime": "--",
          "WaitTimeString": "-- min",
          "FirstTracks": "No",
          "Hours": {
            "Sunday": {
              "Open": "8:30 AM",
              "Close": "4:00 PM"
            },
            "Monday": {
              "Open": "9:00 AM",
              "Close": "4:00 PM"
            },
            "Tuesday": {
              "Open": "9:00 AM",
              "Close": "4:00 PM"
            },
            "Wednesday": {
              "Open": "9:00 AM",
              "Close": "4:00 PM"
            },
            "Thursday": {
              "Open": "9:00 AM",
              "Close": "4:00 PM"
            },
            "Friday": {
              "Open": "9:00 AM",
              "Close": "4:00 PM"
            },
            "Saturday": {
              "Open": "8:30 AM",
              "Close": "4:00 PM"
            }
          }
        },
        {
          "Name": "Tamarack",
          "Status": "Closed",
          "IsOpen": false,
          "LiftType": "Triple Chair",
          "WaitTime": "--",
          "WaitTimeString": "-- min",
          "FirstTracks": "No",
          "Hours": {
            "Sunday": {
              "Open": "8:30 AM",
              "Close": "4:00 PM"
            },
            "Monday": {
              "Open": "9:00 AM",
              "Close": "4:00 PM"
            },
            "Tuesday": {
              "Open": "9:00 AM",
              "Close": "4:00 PM"
            },
            "Wednesday": {
              "Open": "9:00 AM",
              "Close": "4:00 PM"
            },
            "Thursday": {
              "Open": "9:00 AM",
              "Close": "4:00 PM"
            },
            "Friday": {
              "Open": "9:00 AM",
              "Close": "4:00 PM"
            },
            "Saturday": {
              "Open": "8:30 AM",
              "Close": "4:00 PM"
            }
          }
        },
        {
          "Name": "Theodore Carpet",
          "Status": "Closed",
          "IsOpen": false,
          "LiftType": "Magic Carpet",
          "WaitTime": "--",
          "WaitTimeString": "-- min",
          "FirstTracks": "No",
          "Hours": {
            "Sunday": {
              "Open": "8:30 AM",
              "Close": "4:00 PM"
            },
            "Monday": {
              "Open": "9:00 AM",
              "Close": "4:00 PM"
            },
            "Tuesday": {
              "Open": "9:00 AM",
              "Close": "4:00 PM"
            },
            "Wednesday": {
              "Open": "9:00 AM",
              "Close": "4:00 PM"
            },
            "Thursday": {
              "Open": "9:00 AM",
              "Close": "4:00 PM"
            },
            "Friday": {
              "Open": "9:00 AM",
              "Close": "4:00 PM"
            },
            "Saturday": {
              "Open": "8:30 AM",
              "Close": "4:00 PM"
            }
          }
        },
        {
          "Name": "Tyro Tube",
          "Status": "Closed",
          "IsOpen": false,
          "LiftType": "Magic Carpet",
          "WaitTime": "--",
          "WaitTimeString": "-- min",
          "FirstTracks": "No",
          "Hours": {
            "Sunday": {
              "Open": "8:30 AM",
              "Close": "4:00 PM"
            },
            "Monday": {
              "Open": "9:00 AM",
              "Close": "4:00 PM"
            },
            "Tuesday": {
              "Open": "9:00 AM",
              "Close": "4:00 PM"
            },
            "Wednesday": {
              "Open": "9:00 AM",
              "Close": "4:00 PM"
            },
            "Thursday": {
              "Open": "9:00 AM",
              "Close": "4:00 PM"
            },
            "Friday": {
              "Open": "9:00 AM",
              "Close": "4:00 PM"
            },
            "Saturday": {
              "Open": "8:30 AM",
              "Close": "4:00 PM"
            }
          }
        },
        {
          "Name": "Oso Carpet",
          "Status": "Closed",
          "IsOpen": false,
          "LiftType": "Magic Carpet",
          "WaitTime": "--",
          "WaitTimeString": "-- min",
          "FirstTracks": "No",
          "Hours": {
            "Sunday": {
              "Open": "8:30 AM",
              "Close": "4:00 PM"
            },
            "Monday": {
              "Open": "9:00 AM",
              "Close": "4:00 PM"
            },
            "Tuesday": {
              "Open": "9:00 AM",
              "Close": "4:00 PM"
            },
            "Wednesday": {
              "Open": "9:00 AM",
              "Close": "4:00 PM"
            },
            "Thursday": {
              "Open": "9:00 AM",
              "Close": "4:00 PM"
            },
            "Friday": {
              "Open": "9:00 AM",
              "Close": "4:00 PM"
            },
            "Saturday": {
              "Open": "8:30 AM",
              "Close": "4:00 PM"
            }
          }
        }
      ]
    },
    {
      "Name": "Lower Mountain",
      "Trails": [
        {
          "Name": "Beeline",
          "Status": "Closed",
          "IsOpen": false,
          "Difficulty": "Intermediate",
          "IsGroomed": false,
          "GroomingStatus": null,
          "TrailType": "Skiing",
          "Moguls": "No",
          "Glades": "No",
          "Touring": "No",
          "RunOfTheDay": "No",
          "SnowMaking": "No",
          "NightSkiing": "No",
          "Nordic": "No",
          "_inspectorGrooming": "No"
        },
        {
          "Name": "Betwixt",
          "Status": "Closed",
          "IsOpen": false,
          "Difficulty": "Intermediate",
          "IsGroomed": false,
          "GroomingStatus": null,
          "TrailType": "Skiing",
          "Moguls": "No",
          "Glades": "No",
          "Touring": "No",
          "RunOfTheDay": "No",
          "SnowMaking": "No",
          "NightSkiing": "No",
          "Nordic": "No",
          "_inspectorGrooming": "No"
        },
        {
          "Name": "Cabot's Run",
          "Status": "Open",
          "IsOpen": true,
          "Difficulty": "Easy",
          "IsGroomed": true,
          "GroomingStatus": "Yes",
          "TrailType": "Skiing",
          "Moguls": "No",
          "Glades": "No",
          "Touring": "No",
          "RunOfTheDay": "No",
          "SnowMaking": "No",
          "NightSkiing": "No",
          "Nordic": "No",
          "_inspectorGrooming": "Yes"
        },
        {
          "Name": "Craig's Run",
          "Status": "Open",
          "IsOpen": true,
          "Difficulty": "Easy",
          "IsGroomed": true,
          "GroomingStatus": "Yes",
          "TrailType": "Skiing",
          "Moguls": "No",
          "Glades": "No",
          "Touring": "No",
          "RunOfTheDay": "No",
          "SnowMaking": "No",
          "NightSkiing": "No",
          "Nordic": "No",
          "_inspectorGrooming": "Yes"
        },
        {
          "Name": "Daniel Webster",
          "Status": "Open",
          "IsOpen": true,
          "Difficulty": "Easy",
          "IsGroomed": true,
          "GroomingStatus": "Yes",
          "TrailType": "Skiing",
          "Moguls": "No",
          "Glades": "No",
          "Touring": "No",
          "RunOfTheDay": "No",
          "SnowMaking": "No",
          "NightSkiing": "No",
          "Nordic": "No",
          "_inspectorGrooming": "Yes"
        },
        {
          "Name": "Duck Soup",
          "Status": "Open",
          "IsOpen": true,
          "Difficulty": "Intermediate",
          "IsGroomed": false,
          "GroomingStatus": null,
          "TrailType": "Skiing",
          "Moguls": "No",
          "Glades": "No",
          "Touring": "No",
          "RunOfTheDay": "No",
          "SnowMaking": "No",
          "NightSkiing": "No",
          "Nordic": "No",
          "_inspectorGrooming": "No"
        },
        {
          "Name": "East Byrnes Side",
          "Status": "Open",
          "IsOpen": true,
          "Difficulty": "Terrain Park",
          "IsGroomed": true,
          "GroomingStatus": "Yes",
          "TrailType": "Skiing",
          "Moguls": "No",
          "Glades": "No",
          "Touring": "No",
          "RunOfTheDay": "No",
          "SnowMaking": "No",
          "NightSkiing": "No",
          "Nordic": "No",
          "_inspectorGrooming": "Yes"
        },
        {
          "Name": "Ethan's Alley",
          "Status": "Open",
          "IsOpen": true,
          "Difficulty": "Easy",
          "IsGroomed": true,
          "GroomingStatus": "Yes",
          "TrailType": "Skiing",
          "Moguls": "No",
          "Glades": "No",
          "Touring": "No",
          "RunOfTheDay": "No",
          "SnowMaking": "No",
          "NightSkiing": "No",
          "Nordic": "No",
          "_inspectorGrooming": "Yes"
        },
        {
          "Name": "Flukey's Run",
          "Status": "Open",
          "IsOpen": true,
          "Difficulty": "Easy",
          "IsGroomed": true,
          "GroomingStatus": "Yes",
          "TrailType": "Skiing",
          "Moguls": "No",
          "Glades": "No",
          "Touring": "No",
          "RunOfTheDay": "No",
          "SnowMaking": "No",
          "NightSkiing": "No",
          "Nordic": "No",
          "_inspectorGrooming": "Yes"
        },
        {
          "Name": "Grizzly Access",
          "Status": "Open",
          "IsOpen": true,
          "Difficulty": "Easy",
          "IsGroomed": true,
          "GroomingStatus": "Yes",
          "TrailType": "Skiing",
          "Moguls": "No",
          "Glades": "No",
          "Touring": "No",
          "RunOfTheDay": "No",
          "SnowMaking": "No",
          "NightSkiing": "No",
          "Nordic": "No",
          "_inspectorGrooming": "Yes"
        },
        {
          "Name": "Hemlock",
          "Status": "Open",
          "IsOpen": true,
          "Difficulty": "Easy",
          "IsGroomed": true,
          "GroomingStatus": "Yes",
          "TrailType": "Skiing",
          "Moguls": "No",
          "Glades": "No",
          "Touring": "No",
          "RunOfTheDay": "No",
          "SnowMaking": "No",
          "NightSkiing": "No",
          "Nordic": "No",
          "_inspectorGrooming": "Yes"
        },
        {
          "Name": "Lad's Legacy",
          "Status": "Open",
          "IsOpen": true,
          "Difficulty": "Easy",
          "IsGroomed": true,
          "GroomingStatus": "Yes",
          "TrailType": "Skiing",
          "Moguls": "No",
          "Glades": "No",
          "Touring": "No",
          "RunOfTheDay": "No",
          "SnowMaking": "No",
          "NightSkiing": "No",
          "Nordic": "No",
          "_inspectorGrooming": "Yes"
        },
        {
          "Name": "Lower Standard",
          "Status": "Open",
          "IsOpen": true,
          "Difficulty": "Intermediate",
          "IsGroomed": true,
          "GroomingStatus": "Yes",
          "TrailType": "Skiing",
          "Moguls": "No",
          "Glades": "No",
          "Touring": "No",
          "RunOfTheDay": "No",
          "SnowMaking": "No",
          "NightSkiing": "No",
          "Nordic": "No",
          "_inspectorGrooming": "Yes"
        },
        {
          "Name": "Lower Tamarack",
          "Status": "Open",
          "IsOpen": true,
          "Difficulty": "Easy",
          "IsGroomed": true,
          "GroomingStatus": "Yes",
          "TrailType": "Skiing",
          "Moguls": "No",
          "Glades": "No",
          "Touring": "No",
          "RunOfTheDay": "No",
          "SnowMaking": "No",
          "NightSkiing": "No",
          "Nordic": "No",
          "_inspectorGrooming": "Yes"
        },
        {
          "Name": "Mark's Run",
          "Status": "Open",
          "IsOpen": true,
          "Difficulty": "Easy",
          "IsGroomed": true,
          "GroomingStatus": "Yes",
          "TrailType": "Skiing",
          "Moguls": "No",
          "Glades": "No",
          "Touring": "No",
          "RunOfTheDay": "No",
          "SnowMaking": "No",
          "NightSkiing": "No",
          "Nordic": "No",
          "_inspectorGrooming": "Yes"
        },
        {
          "Name": "Old Log Road",
          "Status": "Open",
          "IsOpen": true,
          "Difficulty": "Easy",
          "IsGroomed": true,
          "GroomingStatus": "Yes",
          "TrailType": "Skiing",
          "Moguls": "No",
          "Glades": "No",
          "Touring": "No",
          "RunOfTheDay": "No",
          "SnowMaking": "No",
          "NightSkiing": "No",
          "Nordic": "No",
          "_inspectorGrooming": "Yes"
        },
        {
          "Name": "Old Smoothie",
          "Status": "Open",
          "IsOpen": true,
          "Difficulty": "Intermediate",
          "IsGroomed": true,
          "GroomingStatus": "Yes",
          "TrailType": "Skiing",
          "Moguls": "No",
          "Glades": "No",
          "Touring": "No",
          "RunOfTheDay": "No",
          "SnowMaking": "No",
          "NightSkiing": "No",
          "Nordic": "No",
          "_inspectorGrooming": "Yes"
        },
        {
          "Name": "Overpass",
          "Status": "Open",
          "IsOpen": true,
          "Difficulty": "Easy",
          "IsGroomed": true,
          "GroomingStatus": "Yes",
          "TrailType": "Skiing",
          "Moguls": "No",
          "Glades": "No",
          "Touring": "No",
          "RunOfTheDay": "No",
          "SnowMaking": "No",
          "NightSkiing": "No",
          "Nordic": "No",
          "_inspectorGrooming": "Yes"
        },
        {
          "Name": "Runaway",
          "Status": "Open",
          "IsOpen": true,
          "Difficulty": "Easy",
          "IsGroomed": true,
          "GroomingStatus": "Yes",
          "TrailType": "Skiing",
          "Moguls": "No",
          "Glades": "No",
          "Touring": "No",
          "RunOfTheDay": "No",
          "SnowMaking": "No",
          "NightSkiing": "No",
          "Nordic": "No",
          "_inspectorGrooming": "Yes"
        },
        {
          "Name": "Snow Bowl Alley",
          "Status": "Open",
          "IsOpen": true,
          "Difficulty": "Intermediate",
          "IsGroomed": true,
          "GroomingStatus": "Yes",
          "TrailType": "Skiing",
          "Moguls": "No",
          "Glades": "No",
          "Touring": "No",
          "RunOfTheDay": "No",
          "SnowMaking": "No",
          "NightSkiing": "No",
          "Nordic": "No",
          "_inspectorGrooming": "Yes"
        },
        {
          "Name": "Spillway",
          "Status": "Open",
          "IsOpen": true,
          "Difficulty": "Intermediate",
          "IsGroomed": false,
          "GroomingStatus": null,
          "TrailType": "Skiing",
          "Moguls": "No",
          "Glades": "No",
          "Touring": "No",
          "RunOfTheDay": "No",
          "SnowMaking": "No",
          "NightSkiing": "No",
          "Nordic": "No",
          "_inspectorGrooming": "No"
        },
        {
          "Name": "Suntanner",
          "Status": "Open",
          "IsOpen": true,
          "Difficulty": "Intermediate",
          "IsGroomed": true,
          "GroomingStatus": "Yes",
          "TrailType": "Skiing",
          "Moguls": "No",
          "Glades": "No",
          "Touring": "No",
          "RunOfTheDay": "No",
          "SnowMaking": "No",
          "NightSkiing": "No",
          "Nordic": "No",
          "_inspectorGrooming": "Yes"
        },
        {
          "Name": "Tink's Link",
          "Status": "Closed",
          "IsOpen": false,
          "Difficulty": "Intermediate",
          "IsGroomed": false,
          "GroomingStatus": null,
          "TrailType": "Skiing",
          "Moguls": "No",
          "Glades": "No",
          "Touring": "No",
          "RunOfTheDay": "No",
          "SnowMaking": "No",
          "NightSkiing": "No",
          "Nordic": "No",
          "_inspectorGrooming": "No"
        },
        {
          "Name": "Tyrolienne Park",
          "Status": "Open",
          "IsOpen": true,
          "Difficulty": "Terrain Park",
          "IsGroomed": true,
          "GroomingStatus": "Yes",
          "TrailType": "Skiing",
          "Moguls": "No",
          "Glades": "No",
          "Touring": "No",
          "RunOfTheDay": "No",
          "SnowMaking": "No",
          "NightSkiing": "No",
          "Nordic": "No",
          "_inspectorGrooming": "Yes"
        },
        {
          "Name": "Underpass",
          "Status": "Open",
          "IsOpen": true,
          "Difficulty": "Easy",
          "IsGroomed": true,
          "GroomingStatus": "Yes",
          "TrailType": "Skiing",
          "Moguls": "No",
          "Glades": "No",
          "Touring": "No",
          "RunOfTheDay": "No",
          "SnowMaking": "No",
          "NightSkiing": "No",
          "Nordic": "No",
          "_inspectorGrooming": "Yes"
        },
        {
          "Name": "White Birch",
          "Status": "Open",
          "IsOpen": true,
          "Difficulty": "Intermediate",
          "IsGroomed": false,
          "GroomingStatus": null,
          "TrailType": "Skiing",
          "Moguls": "No",
          "Glades": "No",
          "Touring": "No",
          "RunOfTheDay": "No",
          "SnowMaking": "No",
          "NightSkiing": "No",
          "Nordic": "No",
          "_inspectorGrooming": "No"
        },
        {
          "Name": "Yodeler",
          "Status": "Open",
          "IsOpen": true,
          "Difficulty": "Intermediate",
          "IsGroomed": true,
          "GroomingStatus": "Yes",
          "TrailType": "Skiing",
          "Moguls": "No",
          "Glades": "No",
          "Touring": "No",
          "RunOfTheDay": "No",
          "SnowMaking": "No",
          "NightSkiing": "No",
          "Nordic": "No",
          "_inspectorGrooming": "Yes"
        },
        {
          "Name": "Yodeler Express",
          "Status": "Open",
          "IsOpen": true,
          "Difficulty": "Easy",
          "IsGroomed": true,
          "GroomingStatus": "Yes",
          "TrailType": "Skiing",
          "Moguls": "No",
          "Glades": "No",
          "Touring": "No",
          "RunOfTheDay": "No",
          "SnowMaking": "No",
          "NightSkiing": "No",
          "Nordic": "No",
          "_inspectorGrooming": "Yes"
        }
      ],
      "Lifts": [
        {
          "Name": "American Express",
          "Status": "Closed",
          "IsOpen": false,
          "LiftType": "6 Chair",
          "WaitTime": "--",
          "WaitTimeString": "-- min",
          "FirstTracks": "No",
          "Hours": {
            "Sunday": {
              "Open": "8:30 AM",
              "Close": "4:00 PM"
            },
            "Monday": {
              "Open": "9:00 AM",
              "Close": "4:00 PM"
            },
            "Tuesday": {
              "Open": "9:00 AM",
              "Close": "4:00 PM"
            },
            "Wednesday": {
              "Open": "9:00 AM",
              "Close": "4:00 PM"
            },
            "Thursday": {
              "Open": "9:00 AM",
              "Close": "4:00 PM"
            },
            "Friday": {
              "Open": "9:00 AM",
              "Close": "4:00 PM"
            },
            "Saturday": {
              "Open": "8:30 AM",
              "Close": "4:00 PM"
            }
          }
        },
        {
          "Name": "South American",
          "Status": "Closed",
          "IsOpen": false,
          "LiftType": "Quad Chair",
          "WaitTime": "--",
          "WaitTimeString": "-- min",
          "FirstTracks": "No",
          "Hours": {
            "Sunday": {
              "Open": "8:30 AM",
              "Close": "4:00 PM"
            },
            "Monday": {
              "Open": "9:00 AM",
              "Close": "4:00 PM"
            },
            "Tuesday": {
              "Open": "9:00 AM",
              "Close": "4:00 PM"
            },
            "Wednesday": {
              "Open": "9:00 AM",
              "Close": "4:00 PM"
            },
            "Thursday": {
              "Open": "9:00 AM",
              "Close": "4:00 PM"
            },
            "Friday": {
              "Open": "9:00 AM",
              "Close": "4:00 PM"
            },
            "Saturday": {
              "Open": "8:30 AM",
              "Close": "4:00 PM"
            }
          }
        }
      ]
    },
    {
      "Name": "Sun Bowl",
      "Trails": [
        {
          "Name": "91",
          "Status": "Open",
          "IsOpen": true,
          "Difficulty": "Easy",
          "IsGroomed": true,
          "GroomingStatus": "Yes",
          "TrailType": "Skiing",
          "Moguls": "No",
          "Glades": "No",
          "Touring": "No",
          "RunOfTheDay": "No",
          "SnowMaking": "No",
          "NightSkiing": "No",
          "Nordic": "No",
          "_inspectorGrooming": "Yes"
        },
        {
          "Name": "91 Extension",
          "Status": "Open",
          "IsOpen": true,
          "Difficulty": "Easy",
          "IsGroomed": true,
          "GroomingStatus": "Yes",
          "TrailType": "Skiing",
          "Moguls": "No",
          "Glades": "No",
          "Touring": "No",
          "RunOfTheDay": "No",
          "SnowMaking": "No",
          "NightSkiing": "No",
          "Nordic": "No",
          "_inspectorGrooming": "Yes"
        },
        {
          "Name": "Big Ben",
          "Status": "Open",
          "IsOpen": true,
          "Difficulty": "Intermediate",
          "IsGroomed": true,
          "GroomingStatus": "Yes",
          "TrailType": "Skiing",
          "Moguls": "No",
          "Glades": "No",
          "Touring": "No",
          "RunOfTheDay": "No",
          "SnowMaking": "No",
          "NightSkiing": "No",
          "Nordic": "No",
          "_inspectorGrooming": "Yes"
        },
        {
          "Name": "Buster's Trail",
          "Status": "Open",
          "IsOpen": true,
          "Difficulty": "Intermediate",
          "IsGroomed": false,
          "GroomingStatus": null,
          "TrailType": "Skiing",
          "Moguls": "No",
          "Glades": "No",
          "Touring": "No",
          "RunOfTheDay": "No",
          "SnowMaking": "No",
          "NightSkiing": "No",
          "Nordic": "No",
          "_inspectorGrooming": "No"
        },
        {
          "Name": "Churchill Downs",
          "Status": "Open",
          "IsOpen": true,
          "Difficulty": "Easy",
          "IsGroomed": true,
          "GroomingStatus": "Yes",
          "TrailType": "Skiing",
          "Moguls": "No",
          "Glades": "No",
          "Touring": "No",
          "RunOfTheDay": "No",
          "SnowMaking": "No",
          "NightSkiing": "No",
          "Nordic": "No",
          "_inspectorGrooming": "Yes"
        },
        {
          "Name": "Gentle Ben",
          "Status": "Open",
          "IsOpen": true,
          "Difficulty": "Intermediate",
          "IsGroomed": false,
          "GroomingStatus": null,
          "TrailType": "Skiing",
          "Moguls": "No",
          "Glades": "No",
          "Touring": "No",
          "RunOfTheDay": "No",
          "SnowMaking": "No",
          "NightSkiing": "No",
          "Nordic": "No",
          "_inspectorGrooming": "No"
        },
        {
          "Name": "Home Run",
          "Status": "Open",
          "IsOpen": true,
          "Difficulty": "Easy",
          "IsGroomed": true,
          "GroomingStatus": "Yes",
          "TrailType": "Skiing",
          "Moguls": "No",
          "Glades": "No",
          "Touring": "No",
          "RunOfTheDay": "No",
          "SnowMaking": "No",
          "NightSkiing": "No",
          "Nordic": "No",
          "_inspectorGrooming": "Yes"
        },
        {
          "Name": "Lower Down Easter",
          "Status": "Open",
          "IsOpen": true,
          "Difficulty": "Intermediate",
          "IsGroomed": true,
          "GroomingStatus": "Yes",
          "TrailType": "Skiing",
          "Moguls": "No",
          "Glades": "No",
          "Touring": "No",
          "RunOfTheDay": "No",
          "SnowMaking": "No",
          "NightSkiing": "No",
          "Nordic": "No",
          "_inspectorGrooming": "Yes"
        },
        {
          "Name": "Lower Kidderbrook",
          "Status": "Open",
          "IsOpen": true,
          "Difficulty": "Easy",
          "IsGroomed": true,
          "GroomingStatus": "Yes",
          "TrailType": "Skiing",
          "Moguls": "No",
          "Glades": "No",
          "Touring": "No",
          "RunOfTheDay": "No",
          "SnowMaking": "No",
          "NightSkiing": "No",
          "Nordic": "No",
          "_inspectorGrooming": "Yes"
        },
        {
          "Name": "Lower Middlebrook",
          "Status": "Open",
          "IsOpen": true,
          "Difficulty": "Easy",
          "IsGroomed": true,
          "GroomingStatus": "Yes",
          "TrailType": "Skiing",
          "Moguls": "No",
          "Glades": "No",
          "Touring": "No",
          "RunOfTheDay": "No",
          "SnowMaking": "No",
          "NightSkiing": "No",
          "Nordic": "No",
          "_inspectorGrooming": "Yes"
        },
        {
          "Name": "Main Line",
          "Status": "Open",
          "IsOpen": true,
          "Difficulty": "Easy",
          "IsGroomed": false,
          "GroomingStatus": null,
          "TrailType": "Skiing",
          "Moguls": "No",
          "Glades": "No",
          "Touring": "No",
          "RunOfTheDay": "No",
          "SnowMaking": "No",
          "NightSkiing": "No",
          "Nordic": "No",
          "_inspectorGrooming": "No"
        },
        {
          "Name": "Number 6",
          "Status": "Open",
          "IsOpen": true,
          "Difficulty": "Intermediate",
          "IsGroomed": false,
          "GroomingStatus": null,
          "TrailType": "Skiing",
          "Moguls": "No",
          "Glades": "No",
          "Touring": "No",
          "RunOfTheDay": "No",
          "SnowMaking": "No",
          "NightSkiing": "No",
          "Nordic": "No",
          "_inspectorGrooming": "No"
        },
        {
          "Name": "Rick's Catch 22",
          "Status": "Open",
          "IsOpen": true,
          "Difficulty": "Expert",
          "IsGroomed": false,
          "GroomingStatus": null,
          "TrailType": "Skiing",
          "Moguls": "Yes",
          "Glades": "No",
          "Touring": "No",
          "RunOfTheDay": "No",
          "SnowMaking": "No",
          "NightSkiing": "No",
          "Nordic": "No",
          "_inspectorGrooming": "No"
        },
        {
          "Name": "Rising Star",
          "Status": "Open",
          "IsOpen": true,
          "Difficulty": "Expert",
          "IsGroomed": false,
          "GroomingStatus": null,
          "TrailType": "Skiing",
          "Moguls": "Yes",
          "Glades": "No",
          "Touring": "No",
          "RunOfTheDay": "No",
          "SnowMaking": "No",
          "NightSkiing": "No",
          "Nordic": "No",
          "_inspectorGrooming": "No"
        },
        {
          "Name": "Rowley's Run",
          "Status": "Open",
          "IsOpen": true,
          "Difficulty": "Intermediate",
          "IsGroomed": false,
          "GroomingStatus": null,
          "TrailType": "Skiing",
          "Moguls": "No",
          "Glades": "No",
          "Touring": "No",
          "RunOfTheDay": "No",
          "SnowMaking": "No",
          "NightSkiing": "No",
          "Nordic": "No",
          "_inspectorGrooming": "No"
        },
        {
          "Name": "Shortcut Big Ben",
          "Status": "Open",
          "IsOpen": true,
          "Difficulty": "Intermediate",
          "IsGroomed": true,
          "GroomingStatus": "Yes",
          "TrailType": "Skiing",
          "Moguls": "No",
          "Glades": "No",
          "Touring": "No",
          "RunOfTheDay": "No",
          "SnowMaking": "No",
          "NightSkiing": "No",
          "Nordic": "No",
          "_inspectorGrooming": "Yes"
        },
        {
          "Name": "Shortcut Gentle Ben",
          "Status": "Open",
          "IsOpen": true,
          "Difficulty": "Intermediate",
          "IsGroomed": false,
          "GroomingStatus": null,
          "TrailType": "Skiing",
          "Moguls": "No",
          "Glades": "No",
          "Touring": "No",
          "RunOfTheDay": "No",
          "SnowMaking": "No",
          "NightSkiing": "No",
          "Nordic": "No",
          "_inspectorGrooming": "No"
        },
        {
          "Name": "Solstice Way",
          "Status": "Open",
          "IsOpen": true,
          "Difficulty": "Easy",
          "IsGroomed": true,
          "GroomingStatus": "Yes",
          "TrailType": "Skiing",
          "Moguls": "No",
          "Glades": "No",
          "Touring": "No",
          "RunOfTheDay": "No",
          "SnowMaking": "No",
          "NightSkiing": "No",
          "Nordic": "No",
          "_inspectorGrooming": "Yes"
        },
        {
          "Name": "Sunbeam",
          "Status": "Open",
          "IsOpen": true,
          "Difficulty": "Intermediate",
          "IsGroomed": false,
          "GroomingStatus": null,
          "TrailType": "Skiing",
          "Moguls": "Yes",
          "Glades": "No",
          "Touring": "No",
          "RunOfTheDay": "No",
          "SnowMaking": "No",
          "NightSkiing": "No",
          "Nordic": "No",
          "_inspectorGrooming": "No"
        },
        {
          "Name": "Sunriser Supertrail",
          "Status": "Open",
          "IsOpen": true,
          "Difficulty": "Intermediate",
          "IsGroomed": true,
          "GroomingStatus": "Yes",
          "TrailType": "Skiing",
          "Moguls": "No",
          "Glades": "No",
          "Touring": "No",
          "RunOfTheDay": "No",
          "SnowMaking": "No",
          "NightSkiing": "No",
          "Nordic": "No",
          "_inspectorGrooming": "Yes"
        },
        {
          "Name": "Tree Top Way",
          "Status": "Open",
          "IsOpen": true,
          "Difficulty": "Intermediate",
          "IsGroomed": true,
          "GroomingStatus": "Yes",
          "TrailType": "Skiing",
          "Moguls": "No",
          "Glades": "No",
          "Touring": "No",
          "RunOfTheDay": "No",
          "SnowMaking": "No",
          "NightSkiing": "No",
          "Nordic": "No",
          "_inspectorGrooming": "Yes"
        },
        {
          "Name": "Way Home",
          "Status": "Open",
          "IsOpen": true,
          "Difficulty": "Intermediate",
          "IsGroomed": true,
          "GroomingStatus": "Yes",
          "TrailType": "Skiing",
          "Moguls": "No",
          "Glades": "No",
          "Touring": "No",
          "RunOfTheDay": "No",
          "SnowMaking": "No",
          "NightSkiing": "No",
          "Nordic": "No",
          "_inspectorGrooming": "Yes"
        }
      ],
      "Lifts": [
        {
          "Name": "Sunrise Express",
          "Status": "Closed",
          "IsOpen": false,
          "LiftType": "6 Chair",
          "WaitTime": "--",
          "WaitTimeString": "-- min",
          "FirstTracks": "No",
          "Hours": {
            "Sunday": {
              "Open": "8:30 AM",
              "Close": "4:00 PM"
            },
            "Monday": {
              "Open": "9:00 AM",
              "Close": "4:00 PM"
            },
            "Tuesday": {
              "Open": "9:00 AM",
              "Close": "4:00 PM"
            },
            "Wednesday": {
              "Open": "9:00 AM",
              "Close": "4:00 PM"
            },
            "Thursday": {
              "Open": "9:00 AM",
              "Close": "4:00 PM"
            },
            "Friday": {
              "Open": "9:00 AM",
              "Close": "4:00 PM"
            },
            "Saturday": {
              "Open": "8:30 AM",
              "Close": "4:00 PM"
            }
          }
        },
        {
          "Name": "Shooting Star",
          "Status": "Closed",
          "IsOpen": false,
          "LiftType": "6 Chair",
          "WaitTime": "--",
          "WaitTimeString": "-- min",
          "FirstTracks": "No",
          "Hours": {
            "Sunday": {
              "Open": "8:30 AM",
              "Close": "4:00 PM"
            },
            "Monday": {
              "Open": "9:00 AM",
              "Close": "4:00 PM"
            },
            "Tuesday": {
              "Open": "9:00 AM",
              "Close": "4:00 PM"
            },
            "Wednesday": {
              "Open": "9:00 AM",
              "Close": "4:00 PM"
            },
            "Thursday": {
              "Open": "9:00 AM",
              "Close": "4:00 PM"
            },
            "Friday": {
              "Open": "9:00 AM",
              "Close": "4:00 PM"
            },
            "Saturday": {
              "Open": "8:30 AM",
              "Close": "4:00 PM"
            }
          }
        },
        {
          "Name": "Solstice",
          "Status": "Closed",
          "IsOpen": false,
          "LiftType": "Quad Chair",
          "WaitTime": "--",
          "WaitTimeString": "-- min",
          "FirstTracks": "No",
          "Hours": {
            "Sunday": {
              "Open": "8:30 AM",
              "Close": "4:00 PM"
            },
            "Monday": {
              "Open": "9:00 AM",
              "Close": "4:00 PM"
            },
            "Tuesday": {
              "Open": "9:00 AM",
              "Close": "4:00 PM"
            },
            "Wednesday": {
              "Open": "9:00 AM",
              "Close": "4:00 PM"
            },
            "Thursday": {
              "Open": "9:00 AM",
              "Close": "4:00 PM"
            },
            "Friday": {
              "Open": "9:00 AM",
              "Close": "4:00 PM"
            },
            "Saturday": {
              "Open": "8:30 AM",
              "Close": "4:00 PM"
            }
          }
        }
      ]
    },
    {
      "Name": "Uphill Travel",
      "Trails": [
        {
          "Name": "Lower Standard - Uphill",
          "Status": "Open",
          "IsOpen": true,
          "Difficulty": "Easy",
          "IsGroomed": true,
          "GroomingStatus": "Yes",
          "TrailType": "Skiing",
          "Moguls": "No",
          "Glades": "No",
          "Touring": "Yes",
          "RunOfTheDay": "No",
          "SnowMaking": "No",
          "NightSkiing": "No",
          "Nordic": "No",
          "_inspectorGrooming": "Yes"
        },
        {
          "Name": "Lower & Upper Kidderbrook",
          "Status": "Open",
          "IsOpen": true,
          "Difficulty": "Expert",
          "IsGroomed": false,
          "GroomingStatus": null,
          "TrailType": "Skiing",
          "Moguls": "No",
          "Glades": "No",
          "Touring": "Yes",
          "RunOfTheDay": "No",
          "SnowMaking": "No",
          "NightSkiing": "No",
          "Nordic": "No",
          "_inspectorGrooming": "No"
        },
        {
          "Name": "Lower Wanderer, West Meadows, Mike's Way",
          "Status": "Open",
          "IsOpen": true,
          "Difficulty": "Intermediate",
          "IsGroomed": true,
          "GroomingStatus": "Yes",
          "TrailType": "Skiing",
          "Moguls": "No",
          "Glades": "No",
          "Touring": "Yes",
          "RunOfTheDay": "No",
          "SnowMaking": "No",
          "NightSkiing": "No",
          "Nordic": "No",
          "_inspectorGrooming": "Yes"
        },
        {
          "Name": "Old Log Rd, West Meadows, Mike's Way",
          "Status": "Open",
          "IsOpen": true,
          "Difficulty": "Intermediate",
          "IsGroomed": true,
          "GroomingStatus": "Yes",
          "TrailType": "Skiing",
          "Moguls": "No",
          "Glades": "No",
          "Touring": "Yes",
          "RunOfTheDay": "No",
          "SnowMaking": "No",
          "NightSkiing": "No",
          "Nordic": "No",
          "_inspectorGrooming": "Yes"
        },
        {
          "Name": "Sun Bowl, Home Run, 91, Main Base Area",
          "Status": "Open",
          "IsOpen": true,
          "Difficulty": "Intermediate",
          "IsGroomed": true,
          "GroomingStatus": "Yes",
          "TrailType": "Skiing",
          "Moguls": "No",
          "Glades": "No",
          "Touring": "Yes",
          "RunOfTheDay": "No",
          "SnowMaking": "No",
          "NightSkiing": "No",
          "Nordic": "No",
          "_inspectorGrooming": "Yes"
        },
        {
          "Name": "Yodeler, Underpass",
          "Status": "Open",
          "IsOpen": true,
          "Difficulty": "Easy",
          "IsGroomed": true,
          "GroomingStatus": "Yes",
          "TrailType": "Skiing",
          "Moguls": "No",
          "Glades": "No",
          "Touring": "Yes",
          "RunOfTheDay": "No",
          "SnowMaking": "No",
          "NightSkiing": "No",
          "Nordic": "No",
          "_inspectorGrooming": "Yes"
        }
      ],
      "Lifts": []
    },
    {
      "Name": "Upper Mountain",
      "Trails": [
        {
          "Name": "Bear Bottom",
          "Status": "Open",
          "IsOpen": true,
          "Difficulty": "Intermediate",
          "IsGroomed": true,
          "GroomingStatus": "Yes",
          "TrailType": "Skiing",
          "Moguls": "No",
          "Glades": "No",
          "Touring": "No",
          "RunOfTheDay": "No",
          "SnowMaking": "No",
          "NightSkiing": "No",
          "Nordic": "No",
          "_inspectorGrooming": "Yes"
        },
        {
          "Name": "Bear Down",
          "Status": "Open",
          "IsOpen": true,
          "Difficulty": "Extreme Terrain",
          "IsGroomed": false,
          "GroomingStatus": null,
          "TrailType": "Skiing",
          "Moguls": "Yes",
          "Glades": "No",
          "Touring": "No",
          "RunOfTheDay": "No",
          "SnowMaking": "No",
          "NightSkiing": "No",
          "Nordic": "No",
          "_inspectorGrooming": "No"
        },
        {
          "Name": "Big D",
          "Status": "Open",
          "IsOpen": true,
          "Difficulty": "Expert",
          "IsGroomed": false,
          "GroomingStatus": null,
          "TrailType": "Skiing",
          "Moguls": "No",
          "Glades": "No",
          "Touring": "No",
          "RunOfTheDay": "No",
          "SnowMaking": "No",
          "NightSkiing": "No",
          "Nordic": "No",
          "_inspectorGrooming": "No"
        },
        {
          "Name": "Black Bear",
          "Status": "Open",
          "IsOpen": true,
          "Difficulty": "Intermediate",
          "IsGroomed": true,
          "GroomingStatus": "Yes",
          "TrailType": "Skiing",
          "Moguls": "No",
          "Glades": "No",
          "Touring": "No",
          "RunOfTheDay": "No",
          "SnowMaking": "No",
          "NightSkiing": "No",
          "Nordic": "No",
          "_inspectorGrooming": "Yes"
        },
        {
          "Name": "Dino's Drop",
          "Status": "Open",
          "IsOpen": true,
          "Difficulty": "Expert",
          "IsGroomed": false,
          "GroomingStatus": null,
          "TrailType": "Skiing",
          "Moguls": "Yes",
          "Glades": "No",
          "Touring": "No",
          "RunOfTheDay": "No",
          "SnowMaking": "No",
          "NightSkiing": "No",
          "Nordic": "No",
          "_inspectorGrooming": "No"
        },
        {
          "Name": "Drifter Link",
          "Status": "Open",
          "IsOpen": true,
          "Difficulty": "Easy",
          "IsGroomed": true,
          "GroomingStatus": "Yes",
          "TrailType": "Skiing",
          "Moguls": "No",
          "Glades": "No",
          "Touring": "No",
          "RunOfTheDay": "No",
          "SnowMaking": "No",
          "NightSkiing": "No",
          "Nordic": "No",
          "_inspectorGrooming": "Yes"
        },
        {
          "Name": "Frank's Fall Line",
          "Status": "Open",
          "IsOpen": true,
          "Difficulty": "Expert",
          "IsGroomed": true,
          "GroomingStatus": "Yes",
          "TrailType": "Skiing",
          "Moguls": "No",
          "Glades": "No",
          "Touring": "No",
          "RunOfTheDay": "No",
          "SnowMaking": "No",
          "NightSkiing": "No",
          "Nordic": "No",
          "_inspectorGrooming": "Yes"
        },
        {
          "Name": "Free Fall",
          "Status": "Open",
          "IsOpen": true,
          "Difficulty": "Extreme Terrain",
          "IsGroomed": true,
          "GroomingStatus": "Yes",
          "TrailType": "Skiing",
          "Moguls": "Yes",
          "Glades": "No",
          "Touring": "No",
          "RunOfTheDay": "No",
          "SnowMaking": "No",
          "NightSkiing": "No",
          "Nordic": "No",
          "_inspectorGrooming": "Yes"
        },
        {
          "Name": "Get My Drift",
          "Status": "Open",
          "IsOpen": true,
          "Difficulty": "Intermediate",
          "IsGroomed": true,
          "GroomingStatus": "Yes",
          "TrailType": "Skiing",
          "Moguls": "No",
          "Glades": "No",
          "Touring": "No",
          "RunOfTheDay": "No",
          "SnowMaking": "No",
          "NightSkiing": "No",
          "Nordic": "No",
          "_inspectorGrooming": "Yes"
        },
        {
          "Name": "Interstate",
          "Status": "Open",
          "IsOpen": true,
          "Difficulty": "Intermediate",
          "IsGroomed": true,
          "GroomingStatus": "Yes",
          "TrailType": "Skiing",
          "Moguls": "No",
          "Glades": "No",
          "Touring": "No",
          "RunOfTheDay": "No",
          "SnowMaking": "No",
          "NightSkiing": "No",
          "Nordic": "No",
          "_inspectorGrooming": "Yes"
        },
        {
          "Name": "Janeway Junction",
          "Status": "Open",
          "IsOpen": true,
          "Difficulty": "Intermediate",
          "IsGroomed": true,
          "GroomingStatus": "Yes",
          "TrailType": "Skiing",
          "Moguls": "No",
          "Glades": "No",
          "Touring": "No",
          "RunOfTheDay": "No",
          "SnowMaking": "No",
          "NightSkiing": "No",
          "Nordic": "No",
          "_inspectorGrooming": "Yes"
        },
        {
          "Name": "Liftline Cut Through",
          "Status": "Open",
          "IsOpen": true,
          "Difficulty": "Expert",
          "IsGroomed": false,
          "GroomingStatus": null,
          "TrailType": "Skiing",
          "Moguls": "No",
          "Glades": "No",
          "Touring": "No",
          "RunOfTheDay": "No",
          "SnowMaking": "No",
          "NightSkiing": "No",
          "Nordic": "No",
          "_inspectorGrooming": "No"
        },
        {
          "Name": "Lower Drifter",
          "Status": "Open",
          "IsOpen": true,
          "Difficulty": "Intermediate",
          "IsGroomed": true,
          "GroomingStatus": "Yes",
          "TrailType": "Skiing",
          "Moguls": "No",
          "Glades": "No",
          "Touring": "No",
          "RunOfTheDay": "No",
          "SnowMaking": "No",
          "NightSkiing": "No",
          "Nordic": "No",
          "_inspectorGrooming": "Yes"
        },
        {
          "Name": "Lower East Meadow",
          "Status": "Open",
          "IsOpen": true,
          "Difficulty": "Easy",
          "IsGroomed": true,
          "GroomingStatus": "Yes",
          "TrailType": "Skiing",
          "Moguls": "No",
          "Glades": "No",
          "Touring": "No",
          "RunOfTheDay": "No",
          "SnowMaking": "No",
          "NightSkiing": "No",
          "Nordic": "No",
          "_inspectorGrooming": "Yes"
        },
        {
          "Name": "Lower Grizzly Bear",
          "Status": "Open",
          "IsOpen": true,
          "Difficulty": "Intermediate",
          "IsGroomed": true,
          "GroomingStatus": "Yes",
          "TrailType": "Skiing",
          "Moguls": "Yes",
          "Glades": "No",
          "Touring": "No",
          "RunOfTheDay": "No",
          "SnowMaking": "No",
          "NightSkiing": "No",
          "Nordic": "No",
          "_inspectorGrooming": "Yes"
        },
        {
          "Name": "Lower Liftline",
          "Status": "Open",
          "IsOpen": true,
          "Difficulty": "Expert",
          "IsGroomed": false,
          "GroomingStatus": null,
          "TrailType": "Skiing",
          "Moguls": "Yes",
          "Glades": "No",
          "Touring": "No",
          "RunOfTheDay": "No",
          "SnowMaking": "No",
          "NightSkiing": "No",
          "Nordic": "No",
          "_inspectorGrooming": "No"
        },
        {
          "Name": "Lower Slalom Glade",
          "Status": "Open",
          "IsOpen": true,
          "Difficulty": "Extreme Terrain",
          "IsGroomed": false,
          "GroomingStatus": null,
          "TrailType": "Skiing",
          "Moguls": "No",
          "Glades": "No",
          "Touring": "No",
          "RunOfTheDay": "No",
          "SnowMaking": "No",
          "NightSkiing": "No",
          "Nordic": "No",
          "_inspectorGrooming": "No"
        },
        {
          "Name": "Lower Spruce",
          "Status": "Open",
          "IsOpen": true,
          "Difficulty": "Expert",
          "IsGroomed": true,
          "GroomingStatus": "Yes",
          "TrailType": "Skiing",
          "Moguls": "No",
          "Glades": "No",
          "Touring": "No",
          "RunOfTheDay": "No",
          "SnowMaking": "No",
          "NightSkiing": "No",
          "Nordic": "No",
          "_inspectorGrooming": "Yes"
        },
        {
          "Name": "Lower Switchback ",
          "Status": "Open",
          "IsOpen": true,
          "Difficulty": "Expert",
          "IsGroomed": true,
          "GroomingStatus": "Yes",
          "TrailType": "Skiing",
          "Moguls": "No",
          "Glades": "No",
          "Touring": "No",
          "RunOfTheDay": "No",
          "SnowMaking": "No",
          "NightSkiing": "No",
          "Nordic": "No",
          "_inspectorGrooming": "Yes"
        },
        {
          "Name": "Lower Wanderer",
          "Status": "Open",
          "IsOpen": true,
          "Difficulty": "Easy",
          "IsGroomed": true,
          "GroomingStatus": "Yes",
          "TrailType": "Skiing",
          "Moguls": "No",
          "Glades": "No",
          "Touring": "No",
          "RunOfTheDay": "No",
          "SnowMaking": "No",
          "NightSkiing": "No",
          "Nordic": "No",
          "_inspectorGrooming": "Yes"
        },
        {
          "Name": "Lower West Meadow",
          "Status": "Open",
          "IsOpen": true,
          "Difficulty": "Easy",
          "IsGroomed": true,
          "GroomingStatus": "Yes",
          "TrailType": "Skiing",
          "Moguls": "No",
          "Glades": "No",
          "Touring": "No",
          "RunOfTheDay": "No",
          "SnowMaking": "No",
          "NightSkiing": "No",
          "Nordic": "No",
          "_inspectorGrooming": "Yes"
        },
        {
          "Name": "Mike's Cut Through",
          "Status": "Open",
          "IsOpen": true,
          "Difficulty": "Easy",
          "IsGroomed": true,
          "GroomingStatus": "Yes",
          "TrailType": "Skiing",
          "Moguls": "No",
          "Glades": "No",
          "Touring": "No",
          "RunOfTheDay": "No",
          "SnowMaking": "No",
          "NightSkiing": "No",
          "Nordic": "No",
          "_inspectorGrooming": "Yes"
        },
        {
          "Name": "Mike's Way",
          "Status": "Open",
          "IsOpen": true,
          "Difficulty": "Easy",
          "IsGroomed": true,
          "GroomingStatus": "Yes",
          "TrailType": "Skiing",
          "Moguls": "No",
          "Glades": "No",
          "Touring": "No",
          "RunOfTheDay": "No",
          "SnowMaking": "No",
          "NightSkiing": "No",
          "Nordic": "No",
          "_inspectorGrooming": "Yes"
        },
        {
          "Name": "Old Number 8",
          "Status": "Open",
          "IsOpen": true,
          "Difficulty": "Easy",
          "IsGroomed": true,
          "GroomingStatus": "Yes",
          "TrailType": "Skiing",
          "Moguls": "No",
          "Glades": "No",
          "Touring": "No",
          "RunOfTheDay": "No",
          "SnowMaking": "No",
          "NightSkiing": "No",
          "Nordic": "No",
          "_inspectorGrooming": "Yes"
        },
        {
          "Name": "Polar Bear",
          "Status": "Open",
          "IsOpen": true,
          "Difficulty": "Expert",
          "IsGroomed": true,
          "GroomingStatus": "Yes",
          "TrailType": "Skiing",
          "Moguls": "No",
          "Glades": "No",
          "Touring": "No",
          "RunOfTheDay": "No",
          "SnowMaking": "No",
          "NightSkiing": "No",
          "Nordic": "No",
          "_inspectorGrooming": "Yes"
        },
        {
          "Name": "Rimeline",
          "Status": "Open",
          "IsOpen": true,
          "Difficulty": "Expert",
          "IsGroomed": false,
          "GroomingStatus": null,
          "TrailType": "Skiing",
          "Moguls": "No",
          "Glades": "No",
          "Touring": "No",
          "RunOfTheDay": "No",
          "SnowMaking": "No",
          "NightSkiing": "No",
          "Nordic": "No",
          "_inspectorGrooming": "No"
        },
        {
          "Name": "Shooter",
          "Status": "Open",
          "IsOpen": true,
          "Difficulty": "Intermediate",
          "IsGroomed": true,
          "GroomingStatus": "Yes",
          "TrailType": "Skiing",
          "Moguls": "No",
          "Glades": "No",
          "Touring": "No",
          "RunOfTheDay": "No",
          "SnowMaking": "No",
          "NightSkiing": "No",
          "Nordic": "No",
          "_inspectorGrooming": "Yes"
        },
        {
          "Name": "Stevek",
          "Status": "Open",
          "IsOpen": true,
          "Difficulty": "Extreme Terrain",
          "IsGroomed": false,
          "GroomingStatus": null,
          "TrailType": "Skiing",
          "Moguls": "No",
          "Glades": "No",
          "Touring": "No",
          "RunOfTheDay": "No",
          "SnowMaking": "No",
          "NightSkiing": "No",
          "Nordic": "No",
          "_inspectorGrooming": "No"
        },
        {
          "Name": "Sun Bowl Express",
          "Status": "Open",
          "IsOpen": true,
          "Difficulty": "Intermediate",
          "IsGroomed": true,
          "GroomingStatus": "Yes",
          "TrailType": "Skiing",
          "Moguls": "No",
          "Glades": "No",
          "Touring": "No",
          "RunOfTheDay": "No",
          "SnowMaking": "No",
          "NightSkiing": "No",
          "Nordic": "No",
          "_inspectorGrooming": "Yes"
        },
        {
          "Name": "The Chute",
          "Status": "Open",
          "IsOpen": true,
          "Difficulty": "Expert",
          "IsGroomed": true,
          "GroomingStatus": "Yes",
          "TrailType": "Skiing",
          "Moguls": "No",
          "Glades": "No",
          "Touring": "No",
          "RunOfTheDay": "No",
          "SnowMaking": "No",
          "NightSkiing": "No",
          "Nordic": "No",
          "_inspectorGrooming": "Yes"
        },
        {
          "Name": "Upper Down Easter",
          "Status": "Open",
          "IsOpen": true,
          "Difficulty": "Extreme Terrain",
          "IsGroomed": true,
          "GroomingStatus": "Yes",
          "TrailType": "Skiing",
          "Moguls": "No",
          "Glades": "No",
          "Touring": "No",
          "RunOfTheDay": "No",
          "SnowMaking": "No",
          "NightSkiing": "No",
          "Nordic": "No",
          "_inspectorGrooming": "Yes"
        },
        {
          "Name": "Upper Drifter",
          "Status": "Open",
          "IsOpen": true,
          "Difficulty": "Intermediate",
          "IsGroomed": true,
          "GroomingStatus": "Yes",
          "TrailType": "Skiing",
          "Moguls": "No",
          "Glades": "No",
          "Touring": "No",
          "RunOfTheDay": "No",
          "SnowMaking": "No",
          "NightSkiing": "No",
          "Nordic": "No",
          "_inspectorGrooming": "Yes"
        },
        {
          "Name": "Upper East Meadow",
          "Status": "Open",
          "IsOpen": true,
          "Difficulty": "Easy",
          "IsGroomed": true,
          "GroomingStatus": "Yes",
          "TrailType": "Skiing",
          "Moguls": "No",
          "Glades": "No",
          "Touring": "No",
          "RunOfTheDay": "No",
          "SnowMaking": "No",
          "NightSkiing": "No",
          "Nordic": "No",
          "_inspectorGrooming": "Yes"
        },
        {
          "Name": "Upper Grizzly Bear",
          "Status": "Open",
          "IsOpen": true,
          "Difficulty": "Extreme Terrain",
          "IsGroomed": true,
          "GroomingStatus": "Yes",
          "TrailType": "Skiing",
          "Moguls": "Yes",
          "Glades": "No",
          "Touring": "No",
          "RunOfTheDay": "No",
          "SnowMaking": "No",
          "NightSkiing": "No",
          "Nordic": "No",
          "_inspectorGrooming": "Yes"
        },
        {
          "Name": "Upper Kidderbrook",
          "Status": "Open",
          "IsOpen": true,
          "Difficulty": "Expert",
          "IsGroomed": true,
          "GroomingStatus": "Yes",
          "TrailType": "Skiing",
          "Moguls": "No",
          "Glades": "No",
          "Touring": "No",
          "RunOfTheDay": "No",
          "SnowMaking": "No",
          "NightSkiing": "No",
          "Nordic": "No",
          "_inspectorGrooming": "Yes"
        },
        {
          "Name": "Upper Liftline",
          "Status": "Open",
          "IsOpen": true,
          "Difficulty": "Expert",
          "IsGroomed": false,
          "GroomingStatus": null,
          "TrailType": "Skiing",
          "Moguls": "Yes",
          "Glades": "No",
          "Touring": "No",
          "RunOfTheDay": "No",
          "SnowMaking": "No",
          "NightSkiing": "No",
          "Nordic": "No",
          "_inspectorGrooming": "No"
        },
        {
          "Name": "Upper Middlebrook",
          "Status": "Open",
          "IsOpen": true,
          "Difficulty": "Expert",
          "IsGroomed": true,
          "GroomingStatus": "Yes",
          "TrailType": "Skiing",
          "Moguls": "No",
          "Glades": "No",
          "Touring": "No",
          "RunOfTheDay": "No",
          "SnowMaking": "No",
          "NightSkiing": "No",
          "Nordic": "No",
          "_inspectorGrooming": "Yes"
        },
        {
          "Name": "Upper Slalom Glade",
          "Status": "Open",
          "IsOpen": true,
          "Difficulty": "Expert",
          "IsGroomed": false,
          "GroomingStatus": null,
          "TrailType": "Skiing",
          "Moguls": "No",
          "Glades": "No",
          "Touring": "No",
          "RunOfTheDay": "No",
          "SnowMaking": "No",
          "NightSkiing": "No",
          "Nordic": "No",
          "_inspectorGrooming": "No"
        },
        {
          "Name": "Upper Spruce",
          "Status": "Open",
          "IsOpen": true,
          "Difficulty": "Extreme Terrain",
          "IsGroomed": true,
          "GroomingStatus": "Yes",
          "TrailType": "Skiing",
          "Moguls": "No",
          "Glades": "No",
          "Touring": "No",
          "RunOfTheDay": "No",
          "SnowMaking": "No",
          "NightSkiing": "No",
          "Nordic": "No",
          "_inspectorGrooming": "Yes"
        },
        {
          "Name": "Upper Standard",
          "Status": "Open",
          "IsOpen": true,
          "Difficulty": "Expert",
          "IsGroomed": true,
          "GroomingStatus": "Yes",
          "TrailType": "Skiing",
          "Moguls": "Yes",
          "Glades": "No",
          "Touring": "No",
          "RunOfTheDay": "No",
          "SnowMaking": "No",
          "NightSkiing": "No",
          "Nordic": "No",
          "_inspectorGrooming": "Yes"
        },
        {
          "Name": "Upper Switchback",
          "Status": "Open",
          "IsOpen": true,
          "Difficulty": "Expert",
          "IsGroomed": false,
          "GroomingStatus": null,
          "TrailType": "Skiing",
          "Moguls": "No",
          "Glades": "No",
          "Touring": "No",
          "RunOfTheDay": "No",
          "SnowMaking": "No",
          "NightSkiing": "No",
          "Nordic": "No",
          "_inspectorGrooming": "No"
        },
        {
          "Name": "Upper Tamarack",
          "Status": "Open",
          "IsOpen": true,
          "Difficulty": "Expert",
          "IsGroomed": true,
          "GroomingStatus": "Yes",
          "TrailType": "Skiing",
          "Moguls": "No",
          "Glades": "No",
          "Touring": "No",
          "RunOfTheDay": "No",
          "SnowMaking": "No",
          "NightSkiing": "No",
          "Nordic": "No",
          "_inspectorGrooming": "Yes"
        },
        {
          "Name": "Upper Wanderer",
          "Status": "Open",
          "IsOpen": true,
          "Difficulty": "Easy",
          "IsGroomed": false,
          "GroomingStatus": null,
          "TrailType": "Skiing",
          "Moguls": "No",
          "Glades": "No",
          "Touring": "No",
          "RunOfTheDay": "No",
          "SnowMaking": "No",
          "NightSkiing": "No",
          "Nordic": "No",
          "_inspectorGrooming": "No"
        },
        {
          "Name": "Upper West Meadow",
          "Status": "Open",
          "IsOpen": true,
          "Difficulty": "Easy",
          "IsGroomed": true,
          "GroomingStatus": "Yes",
          "TrailType": "Skiing",
          "Moguls": "No",
          "Glades": "No",
          "Touring": "No",
          "RunOfTheDay": "No",
          "SnowMaking": "No",
          "NightSkiing": "No",
          "Nordic": "No",
          "_inspectorGrooming": "Yes"
        },
        {
          "Name": "Work Road",
          "Status": "Open",
          "IsOpen": true,
          "Difficulty": "Easy",
          "IsGroomed": true,
          "GroomingStatus": "Yes",
          "TrailType": "Skiing",
          "Moguls": "No",
          "Glades": "No",
          "Touring": "No",
          "RunOfTheDay": "No",
          "SnowMaking": "No",
          "NightSkiing": "No",
          "Nordic": "No",
          "_inspectorGrooming": "Yes"
        },
        {
          "Name": "World Cup",
          "Status": "Open",
          "IsOpen": true,
          "Difficulty": "Extreme Terrain",
          "IsGroomed": false,
          "GroomingStatus": null,
          "TrailType": "Skiing",
          "Moguls": "Yes",
          "Glades": "No",
          "Touring": "No",
          "RunOfTheDay": "No",
          "SnowMaking": "No",
          "NightSkiing": "No",
          "Nordic": "No",
          "_inspectorGrooming": "No"
        }
      ],
      "Lifts": [
        {
          "Name": "URSA Express",
          "Status": "Closed",
          "IsOpen": false,
          "LiftType": "6 Chair",
          "WaitTime": "--",
          "WaitTimeString": "-- min",
          "FirstTracks": "No",
          "Hours": {
            "Sunday": {
              "Open": "8:30 AM",
              "Close": "4:00 PM"
            },
            "Monday": {
              "Open": "9:00 AM",
              "Close": "4:00 PM"
            },
            "Tuesday": {
              "Open": "9:00 AM",
              "Close": "4:00 PM"
            },
            "Wednesday": {
              "Open": "9:00 AM",
              "Close": "4:00 PM"
            },
            "Thursday": {
              "Open": "9:00 AM",
              "Close": "4:00 PM"
            },
            "Friday": {
              "Open": "9:00 AM",
              "Close": "4:00 PM"
            },
            "Saturday": {
              "Open": "8:30 AM",
              "Close": "4:00 PM"
            }
          }
        },
        {
          "Name": "Gondola",
          "Status": "Closed",
          "IsOpen": false,
          "LiftType": "Gondola",
          "WaitTime": "--",
          "WaitTimeString": "-- min",
          "FirstTracks": "No",
          "Hours": {
            "Sunday": {
              "Open": "8:30 AM",
              "Close": "4:00 PM"
            },
            "Monday": {
              "Open": "9:00 AM",
              "Close": "4:00 PM"
            },
            "Tuesday": {
              "Open": "9:00 AM",
              "Close": "4:00 PM"
            },
            "Wednesday": {
              "Open": "9:00 AM",
              "Close": "4:00 PM"
            },
            "Thursday": {
              "Open": "9:00 AM",
              "Close": "4:00 PM"
            },
            "Friday": {
              "Open": "9:00 AM",
              "Close": "4:00 PM"
            },
            "Saturday": {
              "Open": "8:30 AM",
              "Close": "4:00 PM"
            }
          }
        },
        {
          "Name": "Snow Bowl Express",
          "Status": "Closed",
          "IsOpen": false,
          "LiftType": "High-Speed Quad",
          "WaitTime": "--",
          "WaitTimeString": "-- min",
          "FirstTracks": "No",
          "Hours": {
            "Sunday": {
              "Open": "8:30 AM",
              "Close": "4:00 PM"
            },
            "Monday": {
              "Open": "9:00 AM",
              "Close": "4:00 PM"
            },
            "Tuesday": {
              "Open": "9:00 AM",
              "Close": "4:00 PM"
            },
            "Wednesday": {
              "Open": "9:00 AM",
              "Close": "4:00 PM"
            },
            "Thursday": {
              "Open": "9:00 AM",
              "Close": "4:00 PM"
            },
            "Friday": {
              "Open": "9:00 AM",
              "Close": "4:00 PM"
            },
            "Saturday": {
              "Open": "8:30 AM",
              "Close": "4:00 PM"
            }
          }
        }
      ]
    }
  ],
  "Lifts": [
    {
      "Name": "Cub Carpet",
      "Status": "Closed",
      "IsOpen": false,
      "LiftType": "Magic Carpet",
      "WaitTime": "--",
      "WaitTimeString": "-- min",
      "FirstTracks": "No",
      "Hours": {
        "Sunday": {
          "Open": "8:30 AM",
          "Close": "4:00 PM"
        },
        "Monday": {
          "Open": "9:00 AM",
          "Close": "4:00 PM"
        },
        "Tuesday": {
          "Open": "9:00 AM",
          "Close": "4:00 PM"
        },
        "Wednesday": {
          "Open": "9:00 AM",
          "Close": "4:00 PM"
        },
        "Thursday": {
          "Open": "9:00 AM",
          "Close": "4:00 PM"
        },
        "Friday": {
          "Open": "9:00 AM",
          "Close": "4:00 PM"
        },
        "Saturday": {
          "Open": "8:30 AM",
          "Close": "4:00 PM"
        }
      }
    },
    {
      "Name": "Villager",
      "Status": "Closed",
      "IsOpen": false,
      "LiftType": "Double",
      "WaitTime": "--",
      "WaitTimeString": "-- min",
      "FirstTracks": "No",
      "Hours": {
        "Sunday": {
          "Open": "8:30 AM",
          "Close": "4:00 PM"
        },
        "Monday": {
          "Open": "9:00 AM",
          "Close": "4:00 PM"
        },
        "Tuesday": {
          "Open": "9:00 AM",
          "Close": "4:00 PM"
        },
        "Wednesday": {
          "Open": "9:00 AM",
          "Close": "4:00 PM"
        },
        "Thursday": {
          "Open": "9:00 AM",
          "Close": "4:00 PM"
        },
        "Friday": {
          "Open": "9:00 AM",
          "Close": "4:00 PM"
        },
        "Saturday": {
          "Open": "8:30 AM",
          "Close": "4:00 PM"
        }
      }
    },
    {
      "Name": "Tamarack",
      "Status": "Closed",
      "IsOpen": false,
      "LiftType": "Triple Chair",
      "WaitTime": "--",
      "WaitTimeString": "-- min",
      "FirstTracks": "No",
      "Hours": {
        "Sunday": {
          "Open": "8:30 AM",
          "Close": "4:00 PM"
        },
        "Monday": {
          "Open": "9:00 AM",
          "Close": "4:00 PM"
        },
        "Tuesday": {
          "Open": "9:00 AM",
          "Close": "4:00 PM"
        },
        "Wednesday": {
          "Open": "9:00 AM",
          "Close": "4:00 PM"
        },
        "Thursday": {
          "Open": "9:00 AM",
          "Close": "4:00 PM"
        },
        "Friday": {
          "Open": "9:00 AM",
          "Close": "4:00 PM"
        },
        "Saturday": {
          "Open": "8:30 AM",
          "Close": "4:00 PM"
        }
      }
    },
    {
      "Name": "Theodore Carpet",
      "Status": "Closed",
      "IsOpen": false,
      "LiftType": "Magic Carpet",
      "WaitTime": "--",
      "WaitTimeString": "-- min",
      "FirstTracks": "No",
      "Hours": {
        "Sunday": {
          "Open": "8:30 AM",
          "Close": "4:00 PM"
        },
        "Monday": {
          "Open": "9:00 AM",
          "Close": "4:00 PM"
        },
        "Tuesday": {
          "Open": "9:00 AM",
          "Close": "4:00 PM"
        },
        "Wednesday": {
          "Open": "9:00 AM",
          "Close": "4:00 PM"
        },
        "Thursday": {
          "Open": "9:00 AM",
          "Close": "4:00 PM"
        },
        "Friday": {
          "Open": "9:00 AM",
          "Close": "4:00 PM"
        },
        "Saturday": {
          "Open": "8:30 AM",
          "Close": "4:00 PM"
        }
      }
    },
    {
      "Name": "Tyro Tube",
      "Status": "Closed",
      "IsOpen": false,
      "LiftType": "Magic Carpet",
      "WaitTime": "--",
      "WaitTimeString": "-- min",
      "FirstTracks": "No",
      "Hours": {
        "Sunday": {
          "Open": "8:30 AM",
          "Close": "4:00 PM"
        },
        "Monday": {
          "Open": "9:00 AM",
          "Close": "4:00 PM"
        },
        "Tuesday": {
          "Open": "9:00 AM",
          "Close": "4:00 PM"
        },
        "Wednesday": {
          "Open": "9:00 AM",
          "Close": "4:00 PM"
        },
        "Thursday": {
          "Open": "9:00 AM",
          "Close": "4:00 PM"
        },
        "Friday": {
          "Open": "9:00 AM",
          "Close": "4:00 PM"
        },
        "Saturday": {
          "Open": "8:30 AM",
          "Close": "4:00 PM"
        }
      }
    },
    {
      "Name": "Oso Carpet",
      "Status": "Closed",
      "IsOpen": false,
      "LiftType": "Magic Carpet",
      "WaitTime": "--",
      "WaitTimeString": "-- min",
      "FirstTracks": "No",
      "Hours": {
        "Sunday": {
          "Open": "8:30 AM",
          "Close": "4:00 PM"
        },
        "Monday": {
          "Open": "9:00 AM",
          "Close": "4:00 PM"
        },
        "Tuesday": {
          "Open": "9:00 AM",
          "Close": "4:00 PM"
        },
        "Wednesday": {
          "Open": "9:00 AM",
          "Close": "4:00 PM"
        },
        "Thursday": {
          "Open": "9:00 AM",
          "Close": "4:00 PM"
        },
        "Friday": {
          "Open": "9:00 AM",
          "Close": "4:00 PM"
        },
        "Saturday": {
          "Open": "8:30 AM",
          "Close": "4:00 PM"
        }
      }
    },
    {
      "Name": "American Express",
      "Status": "Closed",
      "IsOpen": false,
      "LiftType": "6 Chair",
      "WaitTime": "--",
      "WaitTimeString": "-- min",
      "FirstTracks": "No",
      "Hours": {
        "Sunday": {
          "Open": "8:30 AM",
          "Close": "4:00 PM"
        },
        "Monday": {
          "Open": "9:00 AM",
          "Close": "4:00 PM"
        },
        "Tuesday": {
          "Open": "9:00 AM",
          "Close": "4:00 PM"
        },
        "Wednesday": {
          "Open": "9:00 AM",
          "Close": "4:00 PM"
        },
        "Thursday": {
          "Open": "9:00 AM",
          "Close": "4:00 PM"
        },
        "Friday": {
          "Open": "9:00 AM",
          "Close": "4:00 PM"
        },
        "Saturday": {
          "Open": "8:30 AM",
          "Close": "4:00 PM"
        }
      }
    },
    {
      "Name": "South American",
      "Status": "Closed",
      "IsOpen": false,
      "LiftType": "Quad Chair",
      "WaitTime": "--",
      "WaitTimeString": "-- min",
      "FirstTracks": "No",
      "Hours": {
        "Sunday": {
          "Open": "8:30 AM",
          "Close": "4:00 PM"
        },
        "Monday": {
          "Open": "9:00 AM",
          "Close": "4:00 PM"
        },
        "Tuesday": {
          "Open": "9:00 AM",
          "Close": "4:00 PM"
        },
        "Wednesday": {
          "Open": "9:00 AM",
          "Close": "4:00 PM"
        },
        "Thursday": {
          "Open": "9:00 AM",
          "Close": "4:00 PM"
        },
        "Friday": {
          "Open": "9:00 AM",
          "Close": "4:00 PM"
        },
        "Saturday": {
          "Open": "8:30 AM",
          "Close": "4:00 PM"
        }
      }
    },
    {
      "Name": "Sunrise Express",
      "Status": "Closed",
      "IsOpen": false,
      "LiftType": "6 Chair",
      "WaitTime": "--",
      "WaitTimeString": "-- min",
      "FirstTracks": "No",
      "Hours": {
        "Sunday": {
          "Open": "8:30 AM",
          "Close": "4:00 PM"
        },
        "Monday": {
          "Open": "9:00 AM",
          "Close": "4:00 PM"
        },
        "Tuesday": {
          "Open": "9:00 AM",
          "Close": "4:00 PM"
        },
        "Wednesday": {
          "Open": "9:00 AM",
          "Close": "4:00 PM"
        },
        "Thursday": {
          "Open": "9:00 AM",
          "Close": "4:00 PM"
        },
        "Friday": {
          "Open": "9:00 AM",
          "Close": "4:00 PM"
        },
        "Saturday": {
          "Open": "8:30 AM",
          "Close": "4:00 PM"
        }
      }
    },
    {
      "Name": "Shooting Star",
      "Status": "Closed",
      "IsOpen": false,
      "LiftType": "6 Chair",
      "WaitTime": "--",
      "WaitTimeString": "-- min",
      "FirstTracks": "No",
      "Hours": {
        "Sunday": {
          "Open": "8:30 AM",
          "Close": "4:00 PM"
        },
        "Monday": {
          "Open": "9:00 AM",
          "Close": "4:00 PM"
        },
        "Tuesday": {
          "Open": "9:00 AM",
          "Close": "4:00 PM"
        },
        "Wednesday": {
          "Open": "9:00 AM",
          "Close": "4:00 PM"
        },
        "Thursday": {
          "Open": "9:00 AM",
          "Close": "4:00 PM"
        },
        "Friday": {
          "Open": "9:00 AM",
          "Close": "4:00 PM"
        },
        "Saturday": {
          "Open": "8:30 AM",
          "Close": "4:00 PM"
        }
      }
    },
    {
      "Name": "Solstice",
      "Status": "Closed",
      "IsOpen": false,
      "LiftType": "Quad Chair",
      "WaitTime": "--",
      "WaitTimeString": "-- min",
      "FirstTracks": "No",
      "Hours": {
        "Sunday": {
          "Open": "8:30 AM",
          "Close": "4:00 PM"
        },
        "Monday": {
          "Open": "9:00 AM",
          "Close": "4:00 PM"
        },
        "Tuesday": {
          "Open": "9:00 AM",
          "Close": "4:00 PM"
        },
        "Wednesday": {
          "Open": "9:00 AM",
          "Close": "4:00 PM"
        },
        "Thursday": {
          "Open": "9:00 AM",
          "Close": "4:00 PM"
        },
        "Friday": {
          "Open": "9:00 AM",
          "Close": "4:00 PM"
        },
        "Saturday": {
          "Open": "8:30 AM",
          "Close": "4:00 PM"
        }
      }
    },
    {
      "Name": "URSA Express",
      "Status": "Closed",
      "IsOpen": false,
      "LiftType": "6 Chair",
      "WaitTime": "--",
      "WaitTimeString": "-- min",
      "FirstTracks": "No",
      "Hours": {
        "Sunday": {
          "Open": "8:30 AM",
          "Close": "4:00 PM"
        },
        "Monday": {
          "Open": "9:00 AM",
          "Close": "4:00 PM"
        },
        "Tuesday": {
          "Open": "9:00 AM",
          "Close": "4:00 PM"
        },
        "Wednesday": {
          "Open": "9:00 AM",
          "Close": "4:00 PM"
        },
        "Thursday": {
          "Open": "9:00 AM",
          "Close": "4:00 PM"
        },
        "Friday": {
          "Open": "9:00 AM",
          "Close": "4:00 PM"
        },
        "Saturday": {
          "Open": "8:30 AM",
          "Close": "4:00 PM"
        }
      }
    },
    {
      "Name": "Gondola",
      "Status": "Closed",
      "IsOpen": false,
      "LiftType": "Gondola",
      "WaitTime": "--",
      "WaitTimeString": "-- min",
      "FirstTracks": "No",
      "Hours": {
        "Sunday": {
          "Open": "8:30 AM",
          "Close": "4:00 PM"
        },
        "Monday": {
          "Open": "9:00 AM",
          "Close": "4:00 PM"
        },
        "Tuesday": {
          "Open": "9:00 AM",
          "Close": "4:00 PM"
        },
        "Wednesday": {
          "Open": "9:00 AM",
          "Close": "4:00 PM"
        },
        "Thursday": {
          "Open": "9:00 AM",
          "Close": "4:00 PM"
        },
        "Friday": {
          "Open": "9:00 AM",
          "Close": "4:00 PM"
        },
        "Saturday": {
          "Open": "8:30 AM",
          "Close": "4:00 PM"
        }
      }
    },
    {
      "Name": "Snow Bowl Express",
      "Status": "Closed",
      "IsOpen": false,
      "LiftType": "High-Speed Quad",
      "WaitTime": "--",
      "WaitTimeString": "-- min",
      "FirstTracks": "No",
      "Hours": {
        "Sunday": {
          "Open": "8:30 AM",
          "Close": "4:00 PM"
        },
        "Monday": {
          "Open": "9:00 AM",
          "Close": "4:00 PM"
        },
        "Tuesday": {
          "Open": "9:00 AM",
          "Close": "4:00 PM"
        },
        "Wednesday": {
          "Open": "9:00 AM",
          "Close": "4:00 PM"
        },
        "Thursday": {
          "Open": "9:00 AM",
          "Close": "4:00 PM"
        },
        "Friday": {
          "Open": "9:00 AM",
          "Close": "4:00 PM"
        },
        "Saturday": {
          "Open": "8:30 AM",
          "Close": "4:00 PM"
        }
      }
    }
  ],
  "IsSuccessful": true,
  "provider": "ikon",
  "apiProvider": "inspector",
  "_inspectorSnowReport": {
    "LastUpdate": "2026-02-14T14:44:50-0500",
    "BaseConditions": "Machine Groomed Packed Powder",
    "Report": "<div><strong>2/14 2:44PM-&nbsp; </strong>Mother Nature was spreading love this Valentines Day with some snow to keep things fresh! For your Sunday, we plan on making turns down 96 open trails. The grooming team is set to hit the slopes overnight, laying fresh stripes across 70 trails. For your way up, all 14 lifts are scheduled to spin at 8:30AM with the possibility of wind related delays. Early access will be available at 7:45AM for First Tracks pass holders.</div><div><br></div><div>Looking for something to do tonight? <a href=\"https://blog.stratton.com/2026/02/live-music-presidents-2026/\">Live Music</a> is everywhere with DJ Zach Mastromarino in the Biergarten at 2-4pm, John Hill in the Sun Bowl Base Lodge from 2-5pm, and Ill Funk bringing the tunes to Grizzly's at 4-7pm. Grab your date, friends, or family and check out our <a href=\"https://www.stratton.com/things-to-do/activities\">Activities</a> including tubing, ice skating, snowmobile tours, climb, and a special <a href=\"https://www.stratton.com/things-to-do/events/nordic-center\">Startlit Snowshoe Hike</a> presented by icebreaker at the Nordic Center from 7-8:30pm, with a free beanie or headband for signing up!</div><div><br></div><div>Snowmakers have been back in action this past week, taking advantage of favorable temperatures to continue building and refreshing coverage across key areas of the mountain. Our team will be taking a brief pause for the weekend but will fire the guns up again soon.</div><div><br></div><div>The Betwixt build is officially underway! Snowmakers have been firing snow guns on Betwixt all week long to build that base and add more snow for features. The park Crew has been chomping at the bit to get back out there, with hopes of opening the top of Betwixt by mid-week!&nbsp;</div><div><br>Much love to you, Stratton!<br><br></div><div><strong>Safety Tip:</strong> Always stay in control. Remember, space not speed.</div><div><br></div><div><a href=\"https://www.stratton.com/things-to-do/events/presidents-week-vermont\">Presidents Week</a> is here at Stratton, with a full week of skiing, events, and aprs across the mountain. Starting Saturday, February 14, through Sunday, February 22, lifts spin daily at 8:30AM along with live music, snowshoe hikes, snowcat dinners, and activities happening throughout the week. Off the slopes, enjoy tubing, cross-country skiing, ice skating, and more, while the Village comes alive with dining, shopping, and entertainment. Its one of the most exciting weeks of the season, and a perfect time to be at Stratton. Hope to see you here!</div><div><br>With conditions lining up this well, its a good time to take advantage of a few extra perks. Were offering lift tickets up to <strong>50% off every Wednesday and Thursday</strong> this seasonexcluding Presidents Week.<br><br></div><div>Reliable cars are the name of the game; that is why we trust Oliver Subaru and Ford. Made for all seasons and all families, check out <a href=\"https://www.oliverfordofbennington.com/\">Oliver Ford</a> and <a href=\"https://www.oliversubaruofrutland.com/\">Oliver Subaru</a> for year-round reliability!</div><div><br></div><div>Stay and relish the Green Mountains! <a href=\"https://www.stratton.com/the-mountain/vermont-real-estate\">Stratton Real Estate</a> is here to help with all your real estate needs. Make your sweet escape a reality.</div>",
    "AdditionalText": "--",
    "News": "--",
    "Alert": "<div><strong>2:39 PM - Ursa is now open!</strong></div>",
    "StormRadar": "--",
    "StormRadarButtonText": "--",
    "SafetyReport": "--",
    "SafetyReportFrench": "--",
    "LiftNotification": "--",
    "LastUpdatedLift": {
      "URSA Express": "open"
    },
    "OpenTerrainAcres": "643",
    "TotalTerrainAcres": "670",
    "StormTotalIn": "0",
    "StormTotalCM": "0",
    "AnnualAverageSnowfallIn": "150",
    "AnnualAverageSnowfallCm": "381",
    "SnowBaseRangeIn": "26",
    "SnowBaseRangeCM": "66",
    "PreferredBaseReporting": "summit",
    "SeasonTotalIn": "119",
    "SeasonTotalCm": "302",
    "SecondarySeasonTotalIn": "119",
    "SecondarySeasonTotalCm": "302",
    "OpenTerrainHectares": "260",
    "TotalTerrainHectares": "271",
    "TotalOpenTrails": 96,
    "TotalTrails": 99,
    "TotalTrailsMakingSnow": 0,
    "GroomedTrails": 70,
    "TotalOpenLifts": 14,
    "TotalLifts": 14,
    "TotalOpenActivities": 8,
    "TotalActivities": 8,
    "TotalOpenParks": 2,
    "TotalParks": 2,
    "OpenNightParks": 0,
    "TotalNightParks": 0,
    "TotalParkFeatures": 12,
    "OpenNightTrails": 0,
    "TotalNightTrails": 0,
    "TotalOpenBeginnerTrails": 37,
    "TotalBeginnerTrails": 37,
    "TotalOpenIntermediateTrails": 30,
    "TotalIntermediateTrails": 33,
    "TotalOpenAdvancedTrails": 19,
    "TotalAdvancedTrails": 19,
    "TotalOpenExpertTrails": 8,
    "TotalExpertTrails": 8,
    "TotalOpenParkTrails": 2,
    "TotalParkTrails": 2,
    "BaseArea": {
      "Name": "Base",
      "SinceLiftsClosedIn": "0",
      "BaseIn": "26",
      "BaseCm": "66",
      "Last24HoursIn": "0",
      "Last48HoursIn": "0",
      "Last72HoursIn": "8",
      "Last7DaysIn": "8",
      "SinceLiftsClosedCm": "0",
      "Last24HoursCm": "0",
      "Last48HoursCm": "0",
      "Last72HoursCm": "20",
      "Last7DaysCm": "20"
    },
    "MidMountainArea": {
      "Name": "Mid Mountain",
      "SinceLiftsClosedIn": "0",
      "BaseIn": "26",
      "BaseCm": "66",
      "Last24HoursIn": "0",
      "Last48HoursIn": "0",
      "Last72HoursIn": "8",
      "Last7DaysIn": "8",
      "SinceLiftsClosedCm": "0",
      "Last24HoursCm": "0",
      "Last48HoursCm": "0",
      "Last72HoursCm": "20",
      "Last7DaysCm": "20"
    },
    "SummitArea": {
      "Name": "Summit",
      "SinceLiftsClosedIn": "0",
      "BaseIn": "26",
      "BaseCm": "66",
      "Last24HoursIn": "0",
      "Last48HoursIn": "0",
      "Last72HoursIn": "8",
      "Last7DaysIn": "8",
      "SinceLiftsClosedCm": "0",
      "Last24HoursCm": "0",
      "Last48HoursCm": "0",
      "Last72HoursCm": "20",
      "Last7DaysCm": "20"
    },
    "AllMountain": {
      "Last24HoursIn": "0",
      "Last48HoursIn": "0",
      "Last72HoursIn": "8",
      "Last7DaysIn": "8",
      "Last24HoursCm": "0",
      "Last48HoursCm": "0",
      "Last72HoursCm": "20",
      "Last7DaysCm": "20",
      "SinceLiftsClosedIn": "0",
      "SinceLiftsClosedCm": "0"
    },
    "GroomingActive": "true",
    "SnowMakingActive": "false",
    "ApiMetrics": [
      {
        "Name": "Base depth",
        "Imperial": "26.0",
        "Metric": "66.04",
        "Type": "Depth",
        "Location": "summit",
        "Label": "Base",
        "LabelFrench": "--",
        "LastUpdate": "2022-09-13T18:01:47-0400"
      },
      {
        "Name": "Season total",
        "Imperial": "119.0",
        "Metric": "302.26",
        "Type": "Depth",
        "Location": "summit",
        "Label": "Season",
        "LabelFrench": "--",
        "LastUpdate": "2022-09-13T18:01:47-0400"
      }
    ],
    "TotalHalfpipes": 0,
    "OpenHalfpipes": 0
  },
  "_inspectorOperatingStatus": "Open",
  "scrapedAt": "2026-02-15T10:41:27.749Z",
  "sourceLastUpdated": "2026-02-15T05:33:33-0500"
}